main/register.v
`timescale 1ns/1ps

module register_32(rd_data1,rd_data2,source_reg1,source_reg2,dest_reg,write_data,reset,write,clk);

parameter v = 31 ;

input [4:0] source_reg1,source_reg2,dest_reg;
input [v:0]write_data ;
input reset,clk,write;

output [v:0] rd_data1,rd_data2;

reg [v:0] register [0:v];
integer i;

assign rd_data1 = register[source_reg1];
assign rd_data2 = register[source_reg2];

always@(posedge clk)
begin
    if(reset)
    begin
        for(i=0; i<=v; i++)
        register[i]=0;
    end
    else
    begin
        if(write)
        register[dest_reg]<=write_data;
    end
end
endmodule

main/tb_register.v
`timescale 1ns/1ps

module tb_reg;
reg [4:0] source_reg1,source_reg2,dest_reg;
reg [31:0]write_data ;
reg reset,clk,write;
integer i;

wire [31:0] rd_data1,rd_data2;

register_32 Re(rd_data1,rd_data2,source_reg1,source_reg2,dest_reg,write_data,reset,write,clk);

initial
clk=0;

always #5 clk=~clk;

initial
begin
    reset=1; write=0; 
    #3 reset=0; write=1; 
end

initial
begin
    for(i=0;i<=31;i=i+1)
    begin
        #4 dest_reg=i; write_data=i*10;
        #10 write=0; 
    end

    #20;
    for(i=2;i<=31;i=i+2)
    begin
        source_reg1=i-1; source_reg2=i;
        #5;
    end
end

initial
begin
    $monitor("time=%0d, source_reg1=%0d, source_reg2=%0d, dest_reg=%0d, write_data=%0d, rd_data1=%0d, rd_data2=%0d",$time,source_reg1,source_reg2,dest_reg,write_data,Re.rd_data1,Re.rd_data2);
    $dumpfile("tb_reg.vcd");
    $dumpvars(0,tb_reg);
    #1000 $finish;
end
endmodule

main/tb_reg.vcd
$date
	Wed Jul 22 00:07:18 2026
$end
$version
	Icarus Verilog
$end
$timescale
	1ps
$end
$scope module tb_reg $end
$var wire 32 ! rd_data2 [31:0] $end
$var wire 32 " rd_data1 [31:0] $end
$var reg 1 # clk $end
$var reg 5 $ dest_reg [4:0] $end
$var reg 1 % reset $end
$var reg 5 & source_reg1 [4:0] $end
$var reg 5 ' source_reg2 [4:0] $end
$var reg 1 ( write $end
$var reg 32 ) write_data [31:0] $end
$var integer 32 * i [31:0] $end
$scope module Re $end
$var wire 1 # clk $end
$var wire 5 + dest_reg [4:0] $end
$var wire 32 , rd_data1 [31:0] $end
$var wire 32 - rd_data2 [31:0] $end
$var wire 1 % reset $end
$var wire 5 . source_reg1 [4:0] $end
$var wire 5 / source_reg2 [4:0] $end
$var wire 1 ( write $end
$var wire 32 0 write_data [31:0] $end
$var parameter 32 1 v $end
$var integer 32 2 i [31:0] $end
$upscope $end
$upscope $end
$enddefinitions $end
$comment Show the parameter values. $end
$dumpall
b11111 1
$end
#0
$dumpvars
bx 2
bx 0
bx /
bx .
bx -
bx ,
bx +
b0 *
bx )
0(
bx '
bx &
1%
bx $
0#
bx "
bx !
$end
#3000
1(
0%
#4000
b0 )
b0 0
b0 $
b0 +
#5000
1#
#10000
0#
#14000
b1 *
0(
#15000
1#
#18000
b1010 )
b1010 0
b1 $
b1 +
#20000
0#
#25000
1#
#28000
b10 *
#30000
0#
#32000
b10100 )
b10100 0
b10 $
b10 +
#35000
1#
#40000
0#
#42000
b11 *
#45000
1#
#46000
b11110 )
b11110 0
b11 $
b11 +
#50000
0#
#55000
1#
#56000
b100 *
#60000
b101000 )
b101000 0
b100 $
b100 +
0#
#65000
1#
#70000
0#
b101 *
#74000
b110010 )
b110010 0
b101 $
b101 +
#75000
1#
#80000
0#
#84000
b110 *
#85000
1#
#88000
b111100 )
b111100 0
b110 $
b110 +
#90000
0#
#95000
1#
#98000
b111 *
#100000
0#
#102000
b1000110 )
b1000110 0
b111 $
b111 +
#105000
1#
#110000
0#
#112000
b1000 *
#115000
1#
#116000
b1010000 )
b1010000 0
b1000 $
b1000 +
#120000
0#
#125000
1#
#126000
b1001 *
#130000
b1011010 )
b1011010 0
b1001 $
b1001 +
0#
#135000
1#
#140000
0#
b1010 *
#144000
b1100100 )
b1100100 0
b1010 $
b1010 +
#145000
1#
#150000
0#
#154000
b1011 *
#155000
1#
#158000
b1101110 )
b1101110 0
b1011 $
b1011 +
#160000
0#
#165000
1#
#168000
b1100 *
#170000
0#
#172000
b1111000 )
b1111000 0
b1100 $
b1100 +
#175000
1#
#180000
0#
#182000
b1101 *
#185000
1#
#186000
b10000010 )
b10000010 0
b1101 $
b1101 +
#190000
0#
#195000
1#
#196000
b1110 *
#200000
b10001100 )
b10001100 0
b1110 $
b1110 +
0#
#205000
1#
#210000
0#
b1111 *
#214000
b10010110 )
b10010110 0
b1111 $
b1111 +
#215000
1#
#220000
0#
#224000
b10000 *
#225000
1#
#228000
b10100000 )
b10100000 0
b10000 $
b10000 +
#230000
0#
#235000
1#
#238000
b10001 *
#240000
0#
#242000
b10101010 )
b10101010 0
b10001 $
b10001 +
#245000
1#
#250000
0#
#252000
b10010 *
#255000
1#
#256000
b10110100 )
b10110100 0
b10010 $
b10010 +
#260000
0#
#265000
1#
#266000
b10011 *
#270000
b10111110 )
b10111110 0
b10011 $
b10011 +
0#
#275000
1#
#280000
0#
b10100 *
#284000
b11001000 )
b11001000 0
b10100 $
b10100 +
#285000
1#
#290000
0#
#294000
b10101 *
#295000
1#
#298000
b11010010 )
b11010010 0
b10101 $
b10101 +
#300000
0#
#305000
1#
#308000
b10110 *
#310000
0#
#312000
b11011100 )
b11011100 0
b10110 $
b10110 +
#315000
1#
#320000
0#
#322000
b10111 *
#325000
1#
#326000
b11100110 )
b11100110 0
b10111 $
b10111 +
#330000
0#
#335000
1#
#336000
b11000 *
#340000
b11110000 )
b11110000 0
b11000 $
b11000 +
0#
#345000
1#
#350000
0#
b11001 *
#354000
b11111010 )
b11111010 0
b11001 $
b11001 +
#355000
1#
#360000
0#
#364000
b11010 *
#365000
1#
#368000
b100000100 )
b100000100 0
b11010 $
b11010 +
#370000
0#
#375000
1#
#378000
b11011 *
#380000
0#
#382000
b100001110 )
b100001110 0
b11011 $
b11011 +
#385000
1#
#390000
0#
#392000
b11100 *
#395000
1#
#396000
b100011000 )
b100011000 0
b11100 $
b11100 +
#400000
0#
#405000
1#
#406000
b11101 *
#410000
b100100010 )
b100100010 0
b11101 $
b11101 +
0#
#415000
1#
#420000
0#
b11110 *
#424000
b100101100 )
b100101100 0
b11110 $
b11110 +
#425000
1#
#430000
0#
#434000
b11111 *
#435000
1#
#438000
b100110110 )
b100110110 0
b11111 $
b11111 +
#440000
0#
#445000
1#
#448000
b100000 *
#450000
0#
#455000
1#
#460000
0#
#465000
1#
#468000
b10 '
b10 /
b1 &
b1 .
b10 *
#470000
0#
#473000
b100 '
b100 /
b11 &
b11 .
b100 *
#475000
1#
#478000
b110 '
b110 /
b101 &
b101 .
b110 *
#480000
0#
#483000
b1000 '
b1000 /
b111 &
b111 .
b1000 *
#485000
1#
#488000
b1010 '
b1010 /
b1001 &
b1001 .
b1010 *
#490000
0#
#493000
b1100 '
b1100 /
b1011 &
b1011 .
b1100 *
#495000
1#
#498000
b1110 '
b1110 /
b1101 &
b1101 .
b1110 *
#500000
0#
#503000
b10000 '
b10000 /
b1111 &
b1111 .
b10000 *
#505000
1#
#508000
b10010 '
b10010 /
b10001 &
b10001 .
b10010 *
#510000
0#
#513000
b10100 '
b10100 /
b10011 &
b10011 .
b10100 *
#515000
1#
#518000
b10110 '
b10110 /
b10101 &
b10101 .
b10110 *
#520000
0#
#523000
b11000 '
b11000 /
b10111 &
b10111 .
b11000 *
#525000
1#
#528000
b11010 '
b11010 /
b11001 &
b11001 .
b11010 *
#530000
0#
#533000
b11100 '
b11100 /
b11011 &
b11011 .
b11100 *
#535000
1#
#538000
b11110 '
b11110 /
b11101 &
b11101 .
b11110 *
#540000
0#
#543000
b100000 *
